<Properties StartupConfiguration="{B5F34415-076E-491E-A35F-BC73AA76B446}|Default">
  <MonoDevelop.Ide.Workbench ActiveDocument="AziendaNoleggioBarche/Core/Noleggio.cs">
    <Files>
      <File FileName="AziendaNoleggioBarche/Core/Noleggio.cs" Line="50" Column="39" IsPinned="True" />
      <File FileName="AziendaNoleggioBarche/Core/Consegna.cs" Line="32" Column="90" IsPinned="True" />
      <File FileName="AziendaNoleggioBarche/Core/CalcolatoreTariffaGiornaliera.cs" Line="10" Column="4" IsPinned="True" />
      <File FileName="AziendaNoleggioBarche/Core/CalcolatoreSconto.cs" Line="40" Column="40" IsPinned="True" />
      <File FileName="AziendaNoleggioBarche/Configurazione/Principale.cs" Line="1" Column="1" IsPinned="True" />
    </Files>
  </MonoDevelop.Ide.Workbench>
  <MultiItemStartupConfigurations />
  <MonoDevelop.Ide.Workspace ActiveConfiguration="Debug" />
  <MonoDevelop.Ide.DebuggingService.PinnedWatches />
  <MonoDevelop.Ide.ItemProperties.AziendaNoleggioBarche PreferredExecutionTarget="MonoDevelop.Default" FirstBuild="True" />
  <MonoDevelop.Ide.DebuggingService.Breakpoints>
    <BreakpointStore />
  </MonoDevelop.Ide.DebuggingService.Breakpoints>
</Properties>